agentvault_cli/__init__.py
agentvault_cli/commands/__init__.py
agentvault_cli/commands/config.py
agentvault_cli/commands/discover.py
agentvault_cli/commands/run.py
agentvault_cli/main.py
agentvault_cli/utils.py
agentvault_cli-0.1.1.dist-info/entry_points.txt
agentvault_cli-0.1.1.dist-info/LICENSE
agentvault_cli-0.1.1.dist-info/METADATA
agentvault_cli-0.1.1.dist-info/WHEEL
agentvault_cli-0.1.1.dist-info/RECORD
