Metadata-Version: 2.3
Name: agentvault-cli
Version: 0.1.1
Summary: Command-line client for the AgentVault ecosystem.
License: Apache-2.0
Keywords: ai,agent,a2a,mcp,cli,command-line,client,tool,security,key-management,python,click,rich,developer-tools
Author: Raphael Zbigniew Jeziorny
Author-email: AgentVault@proton.me
Requires-Python: >=3.10,<3.12
Classifier: Development Status :: 3 - Alpha
Classifier: Intended Audience :: Developers
Classifier: Intended Audience :: System Administrators
Classifier: License :: OSI Approved :: Apache Software License
Classifier: Operating System :: OS Independent
Classifier: Programming Language :: Python :: 3
Classifier: Programming Language :: Python :: 3.10
Classifier: Programming Language :: Python :: 3.11
Classifier: Environment :: Console
Classifier: Topic :: Utilities
Classifier: Topic :: Security
Classifier: Topic :: Communications
Classifier: Topic :: Scientific/Engineering :: Artificial Intelligence
Provides-Extra: dev
Requires-Dist: agentvault (>=0.2.0,<0.3.0)
Requires-Dist: click (>=8.0,<9.0)
Requires-Dist: httpx (>=0.27,<0.29)
Requires-Dist: pytest (>=8.0,<9.0) ; extra == "dev"
Requires-Dist: pytest-mock (>=3.12,<4.0) ; extra == "dev"
Requires-Dist: rich (>=13.0,<15.0)
